notifier_botty/__init__.py
notifier_botty/bot.py
notifier_botty-0.3.2.dist-info/METADATA
notifier_botty-0.3.2.dist-info/WHEEL
notifier_botty-0.3.2.dist-info/top_level.txt
notifier_botty-0.3.2.dist-info/RECORD
