Metadata-Version: 2.1
Name: notifier_botty
Version: 0.3.2
Summary: A package for automating experts login and notifications
Author: Dharshan
Author-email: dharshanspn@mail.com
Classifier: Programming Language :: Python :: 3
Classifier: Operating System :: OS Independent
Requires-Python: >=3.6
Requires-Dist: selenium
Requires-Dist: pytz
Requires-Dist: requests
